robust_bias_aware/__init__.py
robust_bias_aware/robust_bias_aware.py
robust_bias_aware/data/__init__.py
robust_bias_aware/data/networks/__init__.py
robust_bias_aware/data/networks/update_inbuilt_ppi_networks.py
robust_bias_aware/data/networks/update_networks.py
robust_bias_aware/robust/__init__.py
robust_bias_aware/robust/main.py
robust_bias_aware/robust/pcst/__init__.py
robust_bias_aware/robust/pcst/edge_ids.py
robust_bias_aware/robust/pcst/pcst_instance.py
robust_bias_aware/robust/pcst/solve_pcst.py
robust_bias_aware/robust/pcst/vertex_ids.py
robust_bias_aware/robust/ppi/__init__.py
robust_bias_aware/robust/ppi/edge_weights.py
robust_bias_aware/robust/ppi/ppi_instance.py
robust_bias_aware/robust/ppi/read_ppi.py
robust_bias_aware/robust/ppi/read_ppi_shuffled.py
robust_bias_aware/robust/ppi/read_terminals.py
robust_bias_aware/robust/steinerdiv/__init__.py
robust_bias_aware/robust/steinerdiv/display_solution_set.py
robust_bias_aware/robust/steinerdiv/min_max_exponential_reduction.py
robust_bias_aware/robust/steinerdiv/solution_set.py
robust_bias_aware-0.0.1.dist-info/LICENSE
robust_bias_aware-0.0.1.dist-info/METADATA
robust_bias_aware-0.0.1.dist-info/WHEEL
robust_bias_aware-0.0.1.dist-info/top_level.txt
robust_bias_aware-0.0.1.dist-info/RECORD
