Metadata-Version: 2.1
Name: robust_bias_aware
Version: 0.0.1
Summary: A python package for ROBUST disease module mining algorithm with study bias correction via the incorporation of bias-aware edge costs.
Home-page: https://github.com/wino6687/pip_conda_demo
Author: S. Sarkar
Author-email: suryadipto.sarkar@fau.de
Classifier: Programming Language :: Python :: 3.7
Classifier: Operating System :: OS Independent
Classifier: License :: OSI Approved :: MIT License
License-File: LICENSE
